async2sync-0.1.1.dist-info/licenses/LICENSE
async_runner/__init__.py
async_runner/main.py
async2sync-0.1.1.dist-info/METADATA
async2sync-0.1.1.dist-info/WHEEL
async2sync-0.1.1.dist-info/top_level.txt
async2sync-0.1.1.dist-info/RECORD
