Metadata-Version: 2.4
Name: async2sync
Version: 0.1.1
Summary: Async Runner - Run async tasks from sync methods
Author-email: Namit Adhikari <official.namit321@gmail.com>
License-Expression: MIT
Project-URL: Homepage, https://github.com/NamitAdhikari/async-runner
Keywords: async,asyncio,event loop,thread-safe,run async from sync,async wrapper,async inside sync
Classifier: Programming Language :: C
Classifier: Programming Language :: Python
Classifier: Programming Language :: Python :: 3
Classifier: Programming Language :: Python :: 3 :: Only
Classifier: Programming Language :: Python :: 3.9
Classifier: Programming Language :: Python :: 3.10
Classifier: Programming Language :: Python :: 3.11
Classifier: Programming Language :: Python :: 3.12
Classifier: Programming Language :: Python :: 3.13
Classifier: Operating System :: OS Independent
Classifier: Framework :: AsyncIO
Classifier: Intended Audience :: Developers
Classifier: Development Status :: 4 - Beta
Requires-Python: >=3.7
License-File: LICENSE
Dynamic: license-file
